link_analyze/__init__.py
link_analyze/analyzer.py
link_analyze/browserthread.py
link_analyze/httprequestsniffer.py
link_analyze/logger.py
link_analyze/main.py
link_analyze/monitor.py
link_analyze/reporter.py
link_analyze/timetable.py
link_analyze/util.py
link_analyze/scapy/__init__.py
link_analyze/scapy/all.py
link_analyze/scapy/ansmachine.py
link_analyze/scapy/as_resolvers.py
link_analyze/scapy/asn1fields.py
link_analyze/scapy/asn1packet.py
link_analyze/scapy/automaton.py
link_analyze/scapy/autorun.py
link_analyze/scapy/base_classes.py
link_analyze/scapy/compat.py
link_analyze/scapy/config.py
link_analyze/scapy/consts.py
link_analyze/scapy/dadict.py
link_analyze/scapy/data.py
link_analyze/scapy/error.py
link_analyze/scapy/fields.py
link_analyze/scapy/main.py
link_analyze/scapy/packet.py
link_analyze/scapy/pipetool.py
link_analyze/scapy/plist.py
link_analyze/scapy/pton_ntop.py
link_analyze/scapy/route.py
link_analyze/scapy/route6.py
link_analyze/scapy/scapypipes.py
link_analyze/scapy/sendrecv.py
link_analyze/scapy/supersocket.py
link_analyze/scapy/themes.py
link_analyze/scapy/utils.py
link_analyze/scapy/utils6.py
link_analyze/scapy/volatile.py
link_analyze/scapy/arch/__init__.py
link_analyze/scapy/arch/common.py
link_analyze/scapy/arch/linux.py
link_analyze/scapy/arch/pcapdnet.py
link_analyze/scapy/arch/solaris.py
link_analyze/scapy/arch/unix.py
link_analyze/scapy/arch/bpf/__init__.py
link_analyze/scapy/arch/bpf/consts.py
link_analyze/scapy/arch/bpf/core.py
link_analyze/scapy/arch/bpf/supersocket.py
link_analyze/scapy/arch/windows/__init__.py
link_analyze/scapy/asn1/__init__.py
link_analyze/scapy/asn1/asn1.py
link_analyze/scapy/asn1/ber.py
link_analyze/scapy/asn1/mib.py
link_analyze/scapy/contrib/__init__.py
link_analyze/scapy/contrib/avs.py
link_analyze/scapy/contrib/bgp.py
link_analyze/scapy/contrib/carp.py
link_analyze/scapy/contrib/cdp.py
link_analyze/scapy/contrib/chdlc.py
link_analyze-0.0.0.6.dist-info/DESCRIPTION.rst
link_analyze-0.0.0.6.dist-info/METADATA
link_analyze-0.0.0.6.dist-info/RECORD
link_analyze-0.0.0.6.dist-info/WHEEL
link_analyze-0.0.0.6.dist-info/entry_points.txt
link_analyze-0.0.0.6.dist-info/metadata.json
link_analyze-0.0.0.6.dist-info/top_level.txt
