Metadata-Version: 2.0
Name: link-analyze
Version: 0.0.0.6
Summary: for link theft analyze, input url , output theft url
Home-page: UNKNOWN
Author: peter
Author-email: peter517@126.com
License: GPL
Platform: UNKNOWN
Requires-Python: >=2.6, !=3.0.*, !=3.1.*, !=3.2.*, !=3.3.*
Requires-Dist: openpyxl (>=2.4.9)
Requires-Dist: selenium (>=3.7.0)
Requires-Dist: scapy (>=2.3.2)
